fhir/bser/__init__.py
fhir/bser/STU1/__init__.py
fhir/bser/STU1/helpers.py
fhir/bser/STU1/extensions/__init__.py
fhir/bser/STU1/profiles/BSeR_ArthritisReferralSupportingInformation.py
fhir/bser/STU1/profiles/BSeR_Coverage.py
fhir/bser/STU1/profiles/BSeR_EducationLevel.py
fhir/bser/STU1/profiles/BSeR_Organization.py
fhir/bser/STU1/profiles/BSeR_PatientConsent.py
fhir/bser/STU1/profiles/BSeR_Practitioner.py
fhir/bser/STU1/profiles/BSeR_ReferralActivityStatus.py
fhir/bser/STU1/profiles/BSeR_ReferralFeedbackComposition.py
fhir/bser/STU1/profiles/BSeR_ReferralFeedbackDocumentBundle.py
fhir/bser/STU1/profiles/BSeR_ReferralInitiatorPractitionerRole.py
fhir/bser/STU1/profiles/BSeR_ReferralMessageBundle.py
fhir/bser/STU1/profiles/BSeR_ReferralMessageHeader.py
fhir/bser/STU1/profiles/BSeR_ReferralRecipientPractitionerRole.py
fhir/bser/STU1/profiles/BSeR_ReferralRequestComposition.py
fhir/bser/STU1/profiles/BSeR_ReferralRequestDocumentBundle.py
fhir/bser/STU1/profiles/BSeR_ReferralServiceRequest.py
fhir/bser/STU1/profiles/BSeR_ReferralTask.py
fhir/bser/STU1/profiles/BSeR_ServiceDeliveryLocation.py
fhir/bser/STU1/profiles/__init__.py
fhir/bser/STU1/tests/__init__.py
fhir.bser-0.1.0.dist-info/METADATA
fhir.bser-0.1.0.dist-info/WHEEL
fhir.bser-0.1.0.dist-info/top_level.txt
fhir.bser-0.1.0.dist-info/RECORD
